stif/__init__.py
stif/data.py
stif/predictor.py
stif/utils.py
stif/variogram_models.py
stif-1.0.2.dist-info/LICENSE
stif-1.0.2.dist-info/METADATA
stif-1.0.2.dist-info/WHEEL
stif-1.0.2.dist-info/top_level.txt
stif-1.0.2.dist-info/RECORD
