Metadata-Version: 2.2
Name: stif
Version: 1.0.2
Summary: Space-Time Interpolation and Forecasting
Home-page: https://github.com/johanneskopton/stif
Author: Johannes Kopton
Author-email: johannes@kopton.org
License: MIT
Keywords: geostatistics kriging variogram spatio-temporal
Classifier: Topic :: Scientific/Engineering
Classifier: Programming Language :: Python :: 3
Classifier: Programming Language :: Python :: 3.9
Classifier: Programming Language :: Python :: 3.10
Classifier: Programming Language :: Python :: 3.11
Classifier: Framework :: tox
Classifier: Operating System :: OS Independent
Classifier: License :: OSI Approved :: MIT License
Requires-Python: >=3.9
License-File: LICENSE
Requires-Dist: numpy<2.0,>=1.19
Requires-Dist: matplotlib
Requires-Dist: pandas
Requires-Dist: scikit-learn
Requires-Dist: numba<=0.60,>=0.54
Requires-Dist: scipy
Provides-Extra: tensorflow
Requires-Dist: tensorflow; extra == "tensorflow"
Requires-Dist: keras; extra == "tensorflow"
Provides-Extra: geo
Requires-Dist: geopandas; extra == "geo"
Requires-Dist: shapely; extra == "geo"
Requires-Dist: rasterio; extra == "geo"
Provides-Extra: interactive
Requires-Dist: ipykernel; extra == "interactive"
Provides-Extra: dev
Requires-Dist: build; extra == "dev"
Requires-Dist: pytest; extra == "dev"
Requires-Dist: pytest-cov; extra == "dev"
Requires-Dist: pytest-html; extra == "dev"
Requires-Dist: genbadge[all]; extra == "dev"
Requires-Dist: flake8; extra == "dev"
Requires-Dist: flake8-html; extra == "dev"
Requires-Dist: autopep8; extra == "dev"
Requires-Dist: pre-commit; extra == "dev"
Requires-Dist: sphinx; extra == "dev"
Requires-Dist: myst-parser; extra == "dev"
Requires-Dist: pydata-sphinx-theme; extra == "dev"
Requires-Dist: tox; extra == "dev"
Requires-Dist: twine; extra == "dev"
Dynamic: author
Dynamic: author-email
Dynamic: classifier
Dynamic: description
Dynamic: description-content-type
Dynamic: home-page
Dynamic: keywords
Dynamic: license
Dynamic: provides-extra
Dynamic: requires-dist
Dynamic: requires-python
Dynamic: summary
